lmtranslator/__init__.py
lmtranslator/flores200.py
lmtranslator/lmtranslator.py
lmtranslator-0.0.10.dist-info/LICENSE
lmtranslator-0.0.10.dist-info/METADATA
lmtranslator-0.0.10.dist-info/WHEEL
lmtranslator-0.0.10.dist-info/top_level.txt
lmtranslator-0.0.10.dist-info/RECORD
